flytekitplugins_kfpytorch-1.16.11-py3.14-nspkg.pth
flytekitplugins/kfpytorch/__init__.py
flytekitplugins/kfpytorch/error_handling.py
flytekitplugins/kfpytorch/pod_template.py
flytekitplugins/kfpytorch/task.py
flytekitplugins_kfpytorch-1.16.11.dist-info/METADATA
flytekitplugins_kfpytorch-1.16.11.dist-info/WHEEL
flytekitplugins_kfpytorch-1.16.11.dist-info/namespace_packages.txt
flytekitplugins_kfpytorch-1.16.11.dist-info/top_level.txt
flytekitplugins_kfpytorch-1.16.11.dist-info/RECORD
